rlalc/CLI.py
rlalc/ImageHandler.py
rlalc/__init__.py
rlalc/main.py
rlalc-0.1.0.dist-info/METADATA
rlalc-0.1.0.dist-info/WHEEL
rlalc-0.1.0.dist-info/entry_points.txt
rlalc-0.1.0.dist-info/top_level.txt
rlalc-0.1.0.dist-info/RECORD
